search/__init__.py
search/main.py
image_download-1.0.0.dist-info/METADATA
image_download-1.0.0.dist-info/WHEEL
image_download-1.0.0.dist-info/top_level.txt
image_download-1.0.0.dist-info/RECORD
