Metadata-Version: 2.1
Name: image-download
Version: 1.0.0
Summary: 구글 이미지 다운로드
Home-page: UNKNOWN
Author: ['Jung Ji-Hyo', 'Joungwoo']
Author-email: cord0318@gmail.com
License: GPL-V3
Keywords: korea,image,image-search,search,google
Platform: UNKNOWN
Classifier: Programming Language :: Python :: 3.8
Classifier: License :: OSI Approved :: GNU General Public License v3 (GPLv3)
Classifier: Development Status :: 5 - Production/Stable
Requires-Python: >=3
Requires-Dist: urllib
Requires-Dist: requests
